Workbook

Sheet Resumo
A1: POC Pick-to-Light: bancada + estações 04 e 27
A2: Arquitetura A (módulos próprios 12 V, barramento RS-485), confirmação pelo coletor. Leitor fixo fora do projeto; identificação por RFID fica como melhoria futura.
A4: Item | B4: Valor | C4: Observação
A5: Fase 1, bancada | B5: ='Fase 1 - Bancada'!E19 -> 3374.8182 | C5: compra das peças, montagem e testes de bancada
A6: Fase 2, estações 04 e 27 | B6: ='Fase 2 - Estações'!E40 -> 16847.012 | C6: materiais, instalação e treinamento, menos o que veio da bancada
A7: Hardware da POC | B7: =B5+B6 -> 20221.83
A8: Contingência | B8: =B7*Premissas!$B$9 -> 2022.183 | C8: percentual na aba Premissas
A9: HARDWARE DA POC COM CONTINGÊNCIA (desembolso) | B9: =B7+B8 -> 22244.013 | C9: valor para aprovação
A11: Software da POC (horas da equipe interna) | B11: =Software!C11 -> 600 | C11: não é desembolso; é a primeira parte do software do projeto
A12: Software da POC (custo interno) | B12: =Software!E11 -> 62269.693
A14: Prazo estimado
A15: Fase 1: compra, montagem, firmware e testes de bancada | B15: 3 a 4 semanas
A16: Fase 2: instalação nas estações 04 e 27 | B16: 1 semana
A17: Operação assistida: medição de erro e caixas por hora | B17: 4 semanas
A18: Decisão sobre as 40 estações | B18: semana 10
A20: Abas: Fase 1 - Bancada · Fase 2 - Estações · Software · Premissas (entradas em azul). Valores em reais, preços de mercado pesquisados em outubro de 2026.

Sheet Premissas
A1: Premissas da POC
A2: Células em azul são entradas; as de fundo amarelo são as premissas principais. Os valores vêm do orçamento completo (Orcamento_PTL.xlsx) e podem ser alterados aqui.
A4: Premissa | B4: Valor | C4: Origem / observação
A5: Custo da hora da equipe interna (R$/h) | B5: 34.930552 | C5: salário + encargos de técnico de manutenção ÷ horas produtivas (aba Premissas do orçamento completo)
A6: Custo da hora do operador (R$/h) | B6: 24.657546 | C6: usado no treinamento dos operadores
A7: Custo da hora de desenvolvimento (R$/h) | B7: 103.78282 | C7: equipe interna de TI (aba Software do orçamento completo)
A8: Frete das compras (% sobre os itens) | B8: 0.05 | C8: estimativa média de frete de e-commerce
A9: Contingência (% sobre o hardware) | B9: 0.1 | C9: reserva para itens não previstos na POC

Sheet Estações
A1: Estações da POC
A3: Item | B3: Estação 04 · Medicamento | C3: Estação 27 · Perfumaria
A4: Total de endereços | B4: 201 | C4: 181
A5: Módulos Q (alto giro 0-3) | B5: 29 | C5: 35
A6: Endereços alto giro 4-5 | B6: 16 | C6: 15
A7: E+Q alto giro 4-5 (2 zonas) | B7: 2 | C7: 2
A8: Endereços baixo giro | B8: 156 | C8: 131
A9: Zonas baixo giro (E+Q) | B9: 4 | C9: 4
A10: Nós de coluna | B10: 10 | C10: 10
A11: Concentrador | B11: 1 | C11: 1
A13: Fonte: tabela wms_endereco de 23/10/2026. As quantidades de compra do piloto incluem 10% de reserva (arredondado para cima), como no orçamento completo.

Sheet Fase 1 - Bancada
A1: Fase 1: bancada de testes
A2: 1 coluna de alto giro e 1 zona de cada tipo, montada em painel de MDF. Valida hardware, firmware e software antes de entrar nas estações.
A4: Item | B4: Base de cálculo | C4: Qtd | D4: Preço unit. (R$) | E4: Total (R$)
A5: Concentrador 12 V completo | B5: gabinete, fonte, placa, alimentação | C5: 1 | D5: 673.73952 | E5: =C5*D5 -> 673.73952
A6: Nó de coluna | B6: 1 prédio de alto giro | C6: 1 | D6: 104.42 | E6: =C6*D6 -> 104.42
A7: Módulos Q | B7: 4 andares (0 a 3) do prédio | C7: 4 | D7: 47.885046 | E7: =C7*D7 -> 191.54018
A8: Módulos E+Q | B8: 1 zona dos andares 4-5 + 1 zona do baixo giro | C8: 2 | D8: 138.31 | E8: =C8*D8 -> 276.62
A9: Sinal luminoso de baixo giro | B9: barra âmbar | C9: 1 | D9: 25.611 | E9: =C9*D9 -> 25.611
A10: Cabo Cat5e (m) | B10: barramento e ligações da bancada | C10: 20 | D10: 2.622623 | E10: =C10*D10 -> 52.452459
A11: Plugs RJ45 | C11: 20 | D11: 0.7099 | E11: =C11*D11 -> 14.198
A12: Painel de MDF com longarina | B12: simula a prateleira | C12: 1 | D12: 66.66 | E12: =C12*D12 -> 66.66
A13: Switch 5 portas | B13: rede da bancada | C13: 1 | D13: 93.63 | E13: =C13*D13 -> 93.63
A14: Ferramentas de rede (crimpar e testar) | B14: compra única, servem para a fase 2 | C14: 1 | D14: 285.99 | E14: =C14*D14 -> 285.99
A15: Bancada de eletrônica (solda, multímetro) | B15: compra única, serve para a fase 2 | C15: 1 | D15: 705.69 | E15: =C15*D15 -> 705.69
A16: Frete das compras | B16: % sobre os itens acima (aba Premissas) | D16: =Premissas!$B$8 -> 0.05 | E16: =SUM(E5:E15)*D16 -> 124.52756
A17: Montagem dos módulos (h) | B17: conc. + nó + 4 Q + 2 E+Q | C17: 5.75 | D17: =Premissas!$B$5 -> 34.930552 | E17: =C17*D17 -> 200.85067
A18: Testes de bancada (h) | B18: acender, confirmar, falha, troca e cadastro de LED, 48 h de operação contínua | C18: 16 | D18: =Premissas!$B$5 -> 34.930552 | E18: =C18*D18 -> 558.88883
A19: TOTAL FASE 1, bancada | E19: =SUM(E5:E18) -> 3374.8182

Sheet Fase 2 - Estações
A1: Fase 2: instalação nas estações 04 e 27
A2: Quantidades das duas estações juntas (com reserva). O concentrador, o nó e os módulos da bancada são reaproveitados na estação 04, e as ferramentas já foram compradas na fase 1: os dois são descontados no fim.
A4: Item | B4: Base de cálculo | C4: Qtd | D4: Preço unit. (R$) | E4: Total (R$)
A5: Materiais e infraestrutura
A6: Módulos Q (alto giro 0-3) | B6: endereços alto giro 0-3 × (1 + reserva) | C6: 71 | D6: 47.885046 | E6: =C6*D6 -> 3399.8383
A7: Nós de coluna (alto giro) | B7: prédios do alto giro × (1 + reserva) | C7: 22 | D7: 104.42 | E7: =C7*D7 -> 2297.24
A8: Módulos E+Q (A4/A5 + zonas baixo giro) | B8: displays E+Q × (1 + reserva) | C8: 14 | D8: 138.31 | E8: =C8*D8 -> 1936.34
A9: Concentradores 12 V | B9: 1 por estação × (1 + reserva) | C9: 3 | D9: 673.73952 | E9: =C9*D9 -> 2021.2186
A10: Cabo de barramento Cat5e (m) | B10: segmentos × m por segmento + 2 saídas × m de saída por estação | C10: 120 | D10: 2.622623 | E10: =C10*D10 -> 314.71475
A11: Plugs RJ45 do barramento | B11: 2 por segmento + 4 por estação (saídas) | C11: 72 | D11: 0.7099 | E11: =C11*D11 -> 51.1128
A12: Canaleta / perfil de fixação (m) | B12: prédios alto giro × (largura × linhas + descida) + 2 lados × corredor + travessia, por estação | C12: 54 | D12: 4.36 | E12: =C12*D12 -> 235.44
A13: Fixações diversas | B13: 1 kit por estação | C13: 2 | D13: 28.52 | E13: =C13*D13 -> 57.04
A14: Sinal luminoso de baixo giro | B14: 1 por estação, ao lado da posição de pega | C14: 2 | D14: 25.611 | E14: =C14*D14 -> 51.222
A15: Cabo de rede até a estação (m) | B15: metros por estação | C15: 100 | D15: 2.622623 | E15: =C15*D15 -> 262.2623
A16: Switch 24 portas | B16: estações ÷ portas por switch (arredondado para cima) | C16: 1 | D16: 769.32 | E16: =C16*D16 -> 769.32
A17: Nobreak do switch | B17: 1 por switch | C17: 1 | D17: 368.1 | E17: =C17*D17 -> 368.1
... A22: Bancada de eletrônica (solda, multímetro) | B22: 1 kit (compra única) | C22: 1 | D22: 705.69 | E22: =C22*D22 -> 705.69
A23: Frete das compras | B23: % sobre os materiais acima (aba Premissas) | D23: =Premissas!$B$8 -> 0.05 | E23: =SUM(E6:E22)*D23 -> 687.32093
A24: Subtotal materiais | E24: =SUM(E6:E23) -> 14433.739
A26: Mão de obra interna e treinamento
A27: Montagem Módulos Q (h) | B27: módulos × h/un | C27: 17.75 | D27: =Premissas!$B$5 -> 34.930552 | E27: =C27*D27 -> 620.0173
A28: Montagem Nós de coluna (h) | B28: nós × h/un | C28: 16.5 | D28: =Premissas!$B$5 -> 34.930552 | E28: =C28*D28 -> 576.35411
A29: Montagem Módulos E+Q (h) | B29: módulos × h/un | C29: 14 | D29: =Premissas!$B$5 -> 34.930552 | E29: =C29*D29 -> 489.02773
A30: Montagem Concentradores (h) | B30: concentradores × h/un | C30: 6 | D30: =Premissas!$B$5 -> 34.930552 | E30: =C30*D30 -> 209.58331
A31: Instalação nas estações (h) | B31: (fixo por estação + Q + nós + E+Q + canaleta) × fator hora extra | C31: 46.68 | D31: =Premissas!$B$5 -> 34.930552 | E31: =C31*D31 -> 1630.5582
A32: Testes e comissionamento (h) | B32: estações × h/estação × fator hora extra | C32: 12 | D32: =Premissas!$B$5 -> 34.930552 | E32: =C32*D32 -> 419.16663
A33: Treinamento dos operadores (h) | B33: estações × turnos × h por operador | C33: 8 | D33: =Premissas!$B$6 -> 24.657546 | E33: =C33*D33 -> 197.26037
A34: Treinamento da manutenção (h) | B34: total da equipe | C34: 16 | D34: =Premissas!$B$5 -> 34.930552 | E34: =C34*D34 -> 558.88883
A35: Subtotal mão de obra e treinamento | E35: =SUM(E27:E34) -> 4700.8565
A37: Descontos (já comprados na fase 1)
A38: (−) Ferramentas já compradas na fase 1 | B38: kit de rede + bancada de eletrônica, com frete | E38: =-('Fase 1 - Bancada'!E14+'Fase 1 - Bancada'!E15)*(1+Premissas!$B$8) -> -1041.264
A39: (−) Módulos da bancada reaproveitados na estação 04 | B39: concentrador, nó, 4 módulos Q e 2 E+Q | E39: =-('Fase 1 - Bancada'!E5+'Fase 1 - Bancada'!E6+'Fase 1 - Bancada'!E7+'Fase 1 - Bancada'!E8) -> -1246.3197
A40: TOTAL FASE 2, estações 04 e 27 | E40: =E24+E35+E38+E39 -> 16847.012

Sheet Software
A1: Software da POC (equipe interna, versão mínima)
A2: Horas da equipe interna. É a primeira parte do software do projeto completo, não um custo a mais; não entra no desembolso de hardware.
A4: Entrega | B4: O que inclui | C4: Horas | D4: R$/h | E4: Custo (R$)
A5: Firmware do concentrador, dos nós e dos E+Q | B5: barramento, endereçamento, diagnóstico, cadastro | C5: 160 | D5: =Premissas!$B$7 -> 103.78282 | E5: =C5*D5 -> 16605.252
A6: Serviço PTL, versão mínima | B6: abrir e fechar caixa, acender, confirmar, sinal de baixo giro | C6: 160 | D6: =Premissas!$B$7 -> 103.78282 | E6: =C6*D6 -> 16605.252
A7: Integração Sybase (leitura dos itens da caixa) | B7: views de leitura e gravação de eventos | C7: 60 | D7: =Premissas!$B$7 -> 103.78282 | E7: =C7*D7 -> 6226.9693
A8: App do coletor (A1), versão mínima | B8: leitura com gatilho e progresso da caixa | C8: 100 | D8: =Premissas!$B$7 -> 103.78282 | E8: =C8*D8 -> 10378.282
A9: Interface de controle, versão mínima | B9: falhas de LED e cadastro por endereço | C9: 40 | D9: =Premissas!$B$7 -> 103.78282 | E9: =C9*D9 -> 4151.3129
A10: Testes da bancada e operação assistida | B10: ajustes durante a POC | C10: 80 | D10: =Premissas!$B$7 -> 103.78282 | E10: =C10*D10 -> 8302.6258
A11: TOTAL SOFTWARE DA POC | C11: =SUM(C5:C10) -> 600 | E11: =SUM(E5:E10) -> 62269.693
