Workbook

Sheet Resumo
A1: Peças do Pick-to-Light com fontes
A2: Preços de lojas on-line consultados em 27/10/2026. Cada componente tem o link nas abas de fontes.
A4: Projeto (Arquitetura A, equipe interna) | B4: POC (R$) | C4: 40 estações (R$) | D4: Observação
A5: Peças e materiais, com frete | B5: =Peças!G36 -> 14698.918 | C5: =Peças!H36 -> 223030.14 | D5: igual à linha de materiais do orçamento completo e do projeto interno
A7: Componentes do projeto
A8: Componentes | B8: 44
A9: Com link e preço lido na página | B9: 41
A10: Sem link (valor estipulado ou serviço a cotar) | B10: 3
A11: Com link, preço não lido (estimado) | B11: 0
A13: RFID futuro (separado, não somado ao projeto) | B13: Piloto (R$) | C13: 40 estações (R$) | D13: Observação
A14: Peças do RFID, com frete | B14: ='RFID - Peças'!G13 -> 1276.1543 | C14: ='RFID - Peças'!H13 -> 24098.063 | D14: melhoria futura; abas RFID - Peças e RFID - Fontes
A16: Componentes do RFID
A17: Componentes | B17: 11
A18: Com link e preço lido na página | B18: 10
A19: Sem link (valor estipulado ou serviço a cotar) | B19: 0
A20: Com link, preço não lido (estimado) | B20: 1
A22: Os preços são de varejo, para 1 unidade, sem frete (o frete entra como percentual). Em compras de centenas de peças vale pedir cotação de atacado às mesmas lojas. Vários itens estavam com 'últimas unidades' na consulta: ver a coluna Observação das abas de fontes.
A23: Abas do projeto: Peças · Fontes · Premissas. Abas do RFID futuro: RFID - Peças · RFID - Fontes.

Sheet Peças
A1: Peças do projeto: Arquitetura A, equipe interna
A2: Preços consultados em 27/10/2026; o preço de cada código soma os componentes da aba Fontes, onde estão a loja, o produto e o link de cada um. Quantidades do orçamento completo (com 10% de reserva). Só peças e materiais: mão de obra e software ficam fora. O RFID (melhoria futura) está nas abas próprias e não entra aqui.
A4: Código | B4: Peça | C4: Unid. | D4: Preço unit. (R$) | E4: Qtd POC (04 e 27 + bancada) | F4: Qtd projeto (40 estações) | G4: Total POC (R$) | H4: Total projeto (R$) | I4: Onde é usada | J4: Fonte
A5: P01 | B5: Display 7 segmentos 4 dígitos TM1637 (usa 3 dígitos, quantidade) | C5: un | D5: =SUMIF(Fontes!$A$2:$A$45,A5,Fontes!$J$2:$J$45) -> 10.97 | E5: 85 | F5: 1685 | G5: =D5*E5 -> 932.45 | H5: =D5*F5 -> 18484.45 | I5: Módulo Q, Módulo E+Q | J5: Usinainfo
A6: P02 | B6: Display 7 segmentos 8 dígitos MAX7219 (endereço) | C6: un | D6: =SUMIF(Fontes!$A$2:$A$45,A6,Fontes!$J$2:$J$45) -> 20.17 | E6: 14 | F6: 277 | G6: =D6*E6 -> 282.38 | H6: =D6*F6 -> 5587.09 | I6: Módulo E+Q | J6: Usinainfo
A7: P03 | B7: Microcontrolador Raspberry Pi Pico (RP2040) | C7: un | D7: =SUMIF(Fontes!$A$2:$A$45,A7,Fontes!$J$2:$J$45) -> 37.9 | E7: 36 | F7: 717 | G7: =D7*E7 -> 1364.4 | H7: =D7*F7 -> 27174.3 | I7: Nó de coluna, Módulo E+Q | J7: MakerHero
A8: P04 | B8: Módulo transceptor RS-485 (MAX485) | C8: un | D8: =SUMIF(Fontes!$A$2:$A$45,A8,Fontes!$J$2:$J$45) -> 8.9 | E8: 42 | F8: 805 | G8: =D8*E8 -> 373.8 | H8: =D8*F8 -> 7164.5 | I8: Nó de coluna, Módulo E+Q, Concentrador (2) | J8: Saravati
A9: P05 | B9: Placa do concentrador RP2040 + Ethernet W5500 (W5500-EVB-Pico) | C9: un | D9: =SUMIF(Fontes!$A$2:$A$45,A9,Fontes!$J$2:$J$45) -> 119.63112 | E9: 3 | F9: 44 | G9: =D9*E9 -> 358.89337 | H9: =D9*F9 -> 5263.7695 | I9: Concentrador | J9: SparkFun (EUA)
A10: P06 | B10: Fonte Mean Well LRS-150-12 (12 V / 12,5 A / 150 W) | C10: un | D10: =SUMIF(Fontes!$A$2:$A$45,A10,Fontes!$J$2:$J$45) -> 189.98 | E10: 3 | F10: 44 | G10: =D10*E10 -> 569.94 | H10: =D10*F10 -> 8359.12 | I10: Concentrador | J10: MCEIG
A11: P08 | B11: Regulador step-down 12 V → 5 V (MP1584, 3 A) | C11: un | D11: =SUMIF(Fontes!$A$2:$A$45,A11,Fontes!$J$2:$J$45) -> 10.9 | E11: 39 | F11: 761 | G11: =D11*E11 -> 425.1 | H11: =D11*F11 -> 8294.9 | I11: Nó de coluna, Módulo E+Q, Concentrador | J11: Saravati
A12: P09 | B12: Botão de confirmação metálico 16 mm com LED 12-24 V (pulsador) | C12: un | D12: =SUMIF(Fontes!$A$2:$A$45,A12,Fontes!$J$2:$J$45) -> 20.75 | E12: 85 | F12: 1685 | G12: =D12*E12 -> 1763.75 | H12: =D12*F12 -> 34963.75 | I12: Módulo Q, Módulo E+Q | J12: Usinainfo
A13: P10 | B13: Conector RJ45 fêmea para placa (90°) | C13: un | D13: =SUMIF(Fontes!$A$2:$A$45,A13,Fontes!$J$2:$J$45) -> 4.5 | E13: 237 | F13: 4690 | G13: =D13*E13 -> 1066.5 | H13: =D13*F13 -> 21105 | I13: Módulo Q (1), Nó (6), E+Q (2), Concentrador (2) | J13: Mult Comercial
A14: P11 | B14: Plug RJ45 Cat5e (macho) | C14: un | D14: =SUMIF(Fontes!$A$2:$A$45,A14,Fontes!$J$2:$J$45) -> 0.7099 | E14: 234 | F14: 4278 | G14: =D14*E14 -> 166.1166 | H14: =D14*F14 -> 3036.9522 | I14: barramento e bancada | J14: KaBuM
A15: P12 | B15: Cabo Cat5e (por metro) | C15: m | D15: =SUMIF(Fontes!$A$2:$A$45,A15,Fontes!$J$2:$J$45) -> 2.622623 | E15: 462 | F15: 7409 | G15: =D15*E15 -> 1211.6518 | H15: =D15*F15 -> 19431.013 | I15: barramento, ligações dos módulos Q, rede até a estação, uplink, bancada | J15: KaBuM
A16: P13 | B16: Carcaça do Módulo Q (impressão 3D, medida padrão compacta) | C16: un | D16: =SUMIF(Fontes!$A$2:$A$45,A16,Fontes!$J$2:$J$45) -> 5 | E16: 71 | F16: 1408 | G16: =D16*E16 -> 355 | H16: =D16*F16 -> 7040 | I16: Módulo Q | J16: Valor estipulado (sem link)
... A34: P49 | B34: Switch 5 portas Gigabit (bancada) | C34: un | D34: =SUMIF(Fontes!$A$2:$A$45,A34,Fontes!$J$2:$J$45) -> 93.63 | E34: 1 | F34: 0 | G34: =D34*E34 -> 93.63 | H34: =D34*F34 -> 0 | I34: bancada da POC | J34: KaBuM
B35: Frete das compras (% da aba Premissas) | G35: =SUM(G5:G34)*Premissas!$B$6 -> 699.9485 | H35: =SUM(H5:H34)*Premissas!$B$6 -> 10620.483
A36: TOTAL | G36: =SUM(G5:G35) -> 14698.918 | H36: =SUM(H5:H35) -> 223030.14
A38: Colunas da POC: estações 04 e 27 com reserva, mais os itens só da bancada (sinal, cabo, plugs, painel de MDF e switch de 5 portas); o concentrador, o nó e os módulos da bancada vão para a estação 04 e não são contados duas vezes.
A39: Fundo amarelo: valor sem preço de loja, por decisão do projeto. P13 e P14: carcaças dos LEDs impressas em 3D, em medida padrão compacta, com valor estipulado. P46: serviço de eletricista, a cotar com a manutenção predial.

Sheet Premissas
A1: Premissas usadas nos preços
A3: Premissa | B3: Valor | C3: Fonte
A4: Câmbio USD/BRL | B4: 5.0371 | C4: renovainvest.com.br/dolar-hoje, fechamento de 23/10/2026 (13h07, mercado fechado)
A5: Fator de importação sobre o valor em US$ | B5: 1.9 | C5: Estimativa para importação formal de eletrônicos (II + IPI + PIS/COFINS + ICMS + frete). Confirmar com Comércio Exterior.
A6: Frete das compras nacionais | B6: 0.05 | C6: Estimativa sobre as peças e a infraestrutura; itens importados já têm frete no fator de importação
A8: Só a placa W5500-EVB-Pico (P05) é importada; as outras peças têm preço em reais em lojas do Brasil.

Sheet Fontes
A1: Código | B1: Componente | C1: Loja | D1: Produto (como aparece na loja) | E1: Link | F1: Preço publicado | G1: Forma do preço | H1: Unidades na embalagem | I1: Qtd por unidade do código | J1: Preço no código (R$) | K1: Data | L1: Observação
A2: P01 | B2: Display TM1637 4 dígitos | C2: Usinainfo | D2: Módulo Display TM1637 LED 7 Segmentos 4 Dígitos Vermelho | E2: https://www.usinainfo.com.br/display-arduino/modulo-display-tm1637-7-segmentos-4-digitos-vermelho-2943.html | F2: 10.97 | G2: Pix | H2: 1 | I2: 1 | J2: =F2/H2*I2 -> 10.97 | K2: 27/10/2026 | L2: cartão R$ 11,55; últimas unidades
A3: P02 | B3: Display MAX7219 8 dígitos | C3: Usinainfo | D3: Módulo Display LED 8 Dígitos com Interface Controle SPI - MAX7219 | E3: https://www.usinainfo.com.br/display-arduino/modulo-display-led-8-digitos-com-interface-controle-spi-max7219-4416.html | F3: 20.17 | G3: Pix | H3: 1 | I3: 1 | J3: =F3/H3*I3 -> 20.17 | K3: 27/10/2026 | L3: cartão R$ 21,23; últimas unidades
A4: P03 | B4: Raspberry Pi Pico | C4: MakerHero | D4: Raspberry Pi Pico (DRA61) | E4: https://www.makerhero.com/produto/raspberry-pi-pico/ | F4: 37.9 | G4: Pix | H4: 1 | I4: 1 | J4: =F4/H4*I4 -> 37.9 | K4: 27/10/2026 | L4: normal R$ 39,90; em estoque
A5: P04 | B5: Módulo MAX485 | C5: Saravati | D5: Módulo Conversor de Dados TTL para RS485 MAX485 | E5: https://www.saravati.com.br/modulo-conversor-de-dados-ttl-para-rs485-max485.html | F5: 8.9 | G5: preço especial | H5: 1 | I5: 1 | J5: =F5/H5*I5 -> 8.9 | K5: 27/10/2026 | L5: normal R$ 14,90; 246 em estoque
A6: P05 | B6: W5500-EVB-Pico | C6: SparkFun (EUA) | D6: W5500-EVB-Pico (DEV-19958) | E6: https://www.sparkfun.com/w5500-evb-pico.html | F6: 12.5 | G6: US$ | H6: 1 | I6: 1 | J6: =F6/H6*I6*Premissas!$B$4*Premissas!$B$5 -> 119.63112 | K6: 27/10/2026 | L6: em estoque; convertido em reais com câmbio × fator de importação (aba Premissas do orçamento completo)
A7: P06 | B7: Fonte LRS-150-12 | C7: MCEIG | D7: LRS-150-12 - Fonte Chaveada 150W 85-264VCA/120-373VCC Saída 12VCC/12.5A - MEAN WELL | E7: https://www.mceig.com.br/produto/lrs-150-12-fonte-chaveada-150w-85-264vca-120-373vcc-saida-12vcc-12-5a-mean-well/ | F7: 189.98 | G7: preço da página | H7: 1 | I7: 1 | J7: =F7/H7*I7 -> 189.98 | K7: 27/10/2026 | L7: em estoque (pode ser encomendado)
A8: P07 | B8: Fonte 5 V 150 W | C8: MCEIG | D8: RSP-150-5 - Fonte Chaveada Fechada 150W 85-264VCA/120-370VCC Saída 5V-30A - MEAN WELL | E8: https://www.mceig.com.br/produto/rsp-150-5-fonte-chaveada-fechada-150w-85-264vca-120-370vcc-saida-5v-30a-mean-well/ | F8: 591.68 | G8: preço da página | H8: 1 | I8: 1 | J8: =F8/H8*I8 -> 591.68 | K8: 27/10/2026 | L8: sob encomenda; a LRS-150-5 não foi encontrada à venda no Brasil; só a variante 5 V usa
A9: P08 | B9: Step-down MP1584 | C9: Saravati | D9: Módulo Mini Conversor De Tensão DC/DC - MP1584EN Step Down | E9: https://www.saravati.com.br/modulo-mini-conversor-de-tensao-dc-dc-mp1584en-step-down.html | F9: 10.9 | G9: preço especial | H9: 1 | I9: 1 | J9: =F9/H9*I9 -> 10.9 | K9: 27/10/2026 | L9: normal R$ 11,90; 106 em estoque; 3 A
A10: P09 | B10: Pulsador inox 16 mm com LED | C10: Usinainfo | D10: Pulsador 16mm LED Vermelho 12-24V Inox Impermeável - MC320 | E10: https://www.usinainfo.com.br/interruptores-e-pulsadores/interruptor-pulsador-16mm-com-led-vermelho-12-24v-em-aco-inox-impermeavel-3134.html | F10: 20.75 | G10: Pix | H10: 1 | I10: 1 | J10: =F10/H10*I10 -> 20.75 | K10: 27/10/2026 | L10: cartão R$ 21,84; últimas unidades
A11: P10 | B11: RJ45 fêmea PCI 90° | C11: Mult Comercial | D11: Conector RJ45 Fêmea 8 vias Blindado 90º PCI - JL46057 | E11: https://www.multcomercial.com.br/conector-jack-rj45-femea-com-8-vias-blindado-90-pci-jl46057.html | F11: 4.5 | G11: Pix | H11: 1 | I11: 1 | J11: =F11/H11*I11 -> 4.5 | K11: 27/10/2026 | L11: cartão R$ 5,00; 285 em estoque. Alternativa sem blindagem Connfly DS1125-S80BP R$ 2,03 (Pix), só 5 em estoque: https://www.multcomercial.com.br/conector-jack-rj45-ds1125-s80bp-8p8c-90-com-08-vias-connfly.html
A12: P11 | B12: Plug RJ45 Cat5e (100 un) | C12: KaBuM | D12: Plug Conector Rj45 Macho Cat 5e 8 Vias - Crimpar (100 Unidades) | E12: https://www.kabum.com.br/produto/328777/plug-conector-rj45-macho-cat-5e-8-vias-crimpar-100-unidades- | F12: 70.99 | G12: Pix | H12: 100 | I12: 1 | J12: =F12/H12*I12 -> 0.7099 | K12: 27/10/2026 | L12: pacote com 100
A13: P12 | B13: Cabo Cat5e 305 m | C13: KaBuM | D13: Cabo de Rede CAT.5e Furukawa SOHOPLUS, 305 Metros, Branco - 23200101 | E13: https://www.kabum.com.br/produto/114681/cabo-de-rede-cat-5e-furukawa-305-metros-branco-23200101 | F13: 799.9 | G13: Pix | H13: 305 | I13: 1 | J13: =F13/H13*I13 -> 2.622623 | K13: 27/10/2026 | L13: normal R$ 1.111,00; restam 10 caixas
A14: P13 | B14: Carcaça 3D do módulo Q | C14: Valor estipulado | D14: Carcaça impressa em 3D, medida padrão compacta (definida pelo projeto) | E14: sem link (valor estipulado) | F14: 5 | G14: valor estipulado | H14: 1 | I14: 1 | J14: =F14/H14*I14 -> 5 | K14: 27/10/2026 | L14: Valor estipulado pelo projeto: carcaça compacta impressa em 3D, sem ocupar espaço na frente da prateleira. Referência do material: filamento PETG 1 kg R$ 169,82 (Pix) na KaBuM, https://www.kabum.com.br/produto/1063679/filamento-1-75mm-petg-basico-1kg-marrom-escuro-para-impressora-3d-com-carretel-reutilizavel-bambu-lab
A15: P14 | B15: Carcaça 3D do módulo E+Q / nó | C15: Valor estipulado | D15: Carcaça impressa em 3D, medida padrão compacta (definida pelo projeto) | E15: sem link (valor estipulado) | F15: 15 | G15: valor estipulado | H15: 1 | I15: 1 | J15: =F15/H15*I15 -> 15 | K15: 27/10/2026 | L15: Valor estipulado pelo projeto: carcaça compacta impressa em 3D para o E+Q e o nó de coluna. Mesma referência de filamento do P13
A16: P15 | B16: Placa fenolite perfurada 7 × 5 cm | C16: Eletrogate | D16: Placa Fenolite Perfurada 7x5cm | E16: https://www.eletrogate.com/placa-fenolite-perfurada-7x5cm | F16: 2.38 | G16: Pix | H16: 1 | I16: 1 | J16: =F16/H16*I16 -> 2.38 | K16: 27/10/2026 | L16: normal R$ 2,50; disponível
A17: P15 | B17: Borne KRE 2 vias | C17: Baú da Eletrônica | D17: Borne KRE KF128 2 Vias - Verde | E17: https://www.baudaeletronica.com.br/produto/borne-kre-kf128-2-vias-verde.html | F17: 1.17 | G17: Pix | H17: 1 | I17: 2 | J17: =F17/H17*I17 -> 2.34 | K17: 27/10/2026 | L17: normal R$ 1,30; 2 por placa (entrada e saída de 12 V)
A18: P16 | B18: Caixa Patola PB-220/70 | C18: Usinainfo | D18: Caixa Patola PB-220/70 para Montagem 71 x 228 x 190 mm | E18: https://www.usinainfo.com.br/caixas-patola/caixa-patola-pb-22070-para-montagem-71-x-228-x-190-mm-4383.html | F18: 166.12 | G18: Pix | H18: 1 | I18: 1 | J18: =F18/H18*I18 -> 166.12 | K18: 27/10/2026 | L18: cartão R$ 174,86; últimas unidades; cabe a fonte LRS-150 (159 × 97 × 30 mm) e as placas
... A45: P49 | B45: Switch 5 portas TL-SG1005D | C45: KaBuM | D45: Switch 5 Portas Gigabit - Tp-link Tl-sg1005d | E45: https://www.kabum.com.br/produto/205611/switch-5-portas-10-100-1000-gigabit-mesa-tl-sg1005d-tp-link | F45: 93.63 | G45: Pix | H45: 1 | I45: 1 | J45: =F45/H45*I45 -> 93.63 | K45: 27/10/2026 | L45: 4x R$ 27,53; vendido por STORN35

Sheet RFID - Peças
A1: RFID futuro: peças (separado do projeto)
A2: Melhoria futura, separada do projeto e fora do investimento inicial. Preços consultados em 27/10/2026, com o link de cada componente na aba RFID - Fontes. Piloto = as mesmas estações 04 e 27.
A4: Código | B4: Peça | C4: Unid. | D4: Preço unit. (R$) | E4: Qtd piloto (04 e 27) | F4: Qtd projeto (40 estações) | G4: Total piloto (R$) | H4: Total projeto (R$) | I4: Onde é usada | J4: Fonte
A5: P22 | B5: Tag NFC NTAG213 adesiva 13,56 MHz | C5: un | D5: =SUMIF('RFID - Fontes'!$A$2:$A$12,A5,'RFID - Fontes'!$J$2:$J$12) -> 2.3741 | E5: 250 | F5: 5000 | G5: =D5*E5 -> 593.525 | H5: =D5*F5 -> 11870.5 | I5: 1 por caixa da frota | J5: Loja RFID
A6: P23 | B6: Proteção da tag na caixa (fita transparente sobre a tag) | C6: un | D6: =SUMIF('RFID - Fontes'!$A$2:$A$12,A6,'RFID - Fontes'!$J$2:$J$12) -> 0.0063 | E6: 250 | F6: 5000 | G6: =D6*E6 -> 1.575 | H6: =D6*F6 -> 31.5 | I6: 1 por caixa da frota | J6: Kalunga
A7: P24 | B7: ESP32-C3 Super Mini (pulseira) | C7: un | D7: =SUMIF('RFID - Fontes'!$A$2:$A$12,A7,'RFID - Fontes'!$J$2:$J$12) -> 29.89 | E7: 5 | F7: 88 | G7: =D7*E7 -> 149.45 | H7: =D7*F7 -> 2630.32 | I7: pulseira | J7: Usinainfo
A8: P25 | B8: Módulo leitor NFC PN532 | C8: un | D8: =SUMIF('RFID - Fontes'!$A$2:$A$12,A8,'RFID - Fontes'!$J$2:$J$12) -> 42.65 | E8: 5 | F8: 88 | G8: =D8*E8 -> 213.25 | H8: =D8*F8 -> 3753.2 | I8: pulseira | J8: MakerHero
A9: P26 | B9: Kit energia pulseira (LiPo + carregador TP4056 + motor de vibração + botão) | C9: kit | D9: =SUMIF('RFID - Fontes'!$A$2:$A$12,A9,'RFID - Fontes'!$J$2:$J$12) -> 34.05 | E9: 5 | F9: 88 | G9: =D9*E9 -> 170.25 | H9: =D9*F9 -> 2996.4 | I9: pulseira | J9: 4 componentes, aba RFID - Fontes (1 estimado)
A10: P27 | B10: Carcaça da pulseira (caixa Patola PB-060) + fita de velcro | C10: un | D10: =SUMIF('RFID - Fontes'!$A$2:$A$12,A10,'RFID - Fontes'!$J$2:$J$12) -> 6.507 | E10: 5 | F10: 88 | G10: =D10*E10 -> 32.535 | H10: =D10*F10 -> 572.616 | I10: pulseira | J10: 2 componentes, aba RFID - Fontes
A11: P45 | B11: Carregador USB 2 portas para pulseiras (RFID futuro) | C11: un | D11: =SUMIF('RFID - Fontes'!$A$2:$A$12,A11,'RFID - Fontes'!$J$2:$J$12) -> 27.4 | E11: 2 | F11: 40 | G11: =D11*E11 -> 54.8 | H11: =D11*F11 -> 1096 | I11: 1 por estação | J11: KaBuM
B12: Frete das compras (% da aba Premissas) | G12: =SUM(G5:G11)*Premissas!$B$6 -> 60.76925 | H12: =SUM(H5:H11)*Premissas!$B$6 -> 1147.5268
A13: TOTAL | G13: =SUM(G5:G12) -> 1276.1543 | H13: =SUM(H5:H12) -> 24098.063
A15: Fundo amarelo: a bateria LiPo do P26 tem link, mas o site não respondeu na consulta; o valor é estimado.

Sheet RFID - Fontes
A1: Código | B1: Componente | C1: Loja | D1: Produto (como aparece na loja) | E1: Link | F1: Preço publicado | G1: Forma do preço | H1: Unidades na embalagem | I1: Qtd por unidade do código | J1: Preço no código (R$) | K1: Data | L1: Observação
A2: P22 | B2: Tag NFC NTAG213 (100 un) | C2: Loja RFID | D2: Etiqueta RFID 13,56 MHz NFC NTAG213 Branca - 100 unidades | E2: https://loja.lojarfid.com.br/13-56-mhz-mf/etiquetas/etiqueta-rfid-13-56-mhz-nfc-ntag213-branca-100-unidades | F2: 237.41 | G2: à vista (boleto) | H2: 100 | I2: 1 | J2: =F2/H2*I2 -> 2.3741 | K2: 27/10/2026 | L2: normal R$ 249,90; lote de 5.000 deve sair mais barato (pedir cotação)
A3: P23 | B3: Fita transparente 45 mm × 45 m (4 rolos) | C3: Kalunga | D3: Fita Adesiva Transparente PP, 45mm x 45m, Stick Tape - PT 4 UN | E3: https://www.kalunga.com.br/prod/fita-adesiva-transparente-pp-45mm-x-45m-stick-tape-pt-4-un/305591 | F3: 18.9 | G3: preço do site | H3: 3000 | I3: 1 | J3: =F3/H3*I3 -> 0.0063 | K3: 27/10/2026 | L3: 4 rolos × 45 m ÷ 6 cm por caixa = 3.000 caixas
A4: P24 | B4: ESP32-C3 Super Mini | C4: Usinainfo | D4: ESP32-C3 Super Mini WiFi Bluetooth USB-C com 13 GPIOs | E4: https://www.usinainfo.com.br/esp32/esp32-c3-super-mini-com-wifi-e-bluetooth-com-usb-c-8967.html | F4: 29.89 | G4: Pix | H4: 1 | I4: 1 | J4: =F4/H4*I4 -> 29.89 | K4: 27/10/2026 | L4: cartão R$ 31,46; últimas unidades
A5: P25 | B5: Kit leitor PN532 | C5: MakerHero | D5: Kit Módulo Leitor RFID NFC PN532 | E5: https://www.makerhero.com/produto/kit-modulo-leitor-rfid-nfc-pn532/ | F5: 42.65 | G5: Pix | H5: 1 | I5: 1 | J5: =F5/H5*I5 -> 42.65 | K5: 27/10/2026 | L5: normal R$ 44,90; em estoque
A6: P26 | B6: Bateria LiPo 3,7 V ~500 mAh | C6: RoboCore | D6: Bateria LiPo 3,7V 530mAh 30C | E6: https://www.robocore.net/loja/baterias/bateria-lipo-1s-530mah-30c | F6: 25 | G6: estimativa (preço não lido) | H6: 1 | I6: 1 | J6: =F6/H6*I6 -> 25 | K6: 27/10/2026 | L6: PREÇO NÃO LIDO: o site não respondeu nas consultas de 27/10/2026 e as outras lojas consultadas estavam sem estoque. Valor estimado, confirmar na página antes da compra
A7: P26 | B7: Carregador TP4056 USB-C | C7: Eletrogate | D7: Módulo Carregador de Baterias de Lítio TP4056 com Proteção - USB-C | E7: https://www.eletrogate.com/modulo-carregador-de-baterias-de-litio-tp4056-com-protecao-usb-c | F7: 4.66 | G7: Pix | H7: 1 | I7: 1 | J7: =F7/H7*I7 -> 4.66 | K7: 27/10/2026 | L7: normal R$ 4,90
A8: P26 | B8: Motor de vibração 1027 | C8: Eletrogate | D8: Micro Motor de Vibração Vibracall 1027 | E8: https://www.eletrogate.com/micro-motor-de-vibracao-vibracall | F8: 4.18 | G8: Pix | H8: 1 | I8: 1 | J8: =F8/H8*I8 -> 4.18 | K8: 27/10/2026 | L8: normal R$ 4,40
A9: P26 | B9: Chave táctil 6 × 6 mm | C9: Eletrogate | D9: Push Button (Chave Táctil) 6x6x6mm | E9: https://www.eletrogate.com/push-button-chave-tactil-6x6x6mm | F9: 0.21 | G9: Pix | H9: 1 | I9: 1 | J9: =F9/H9*I9 -> 0.21 | K9: 27/10/2026 | L9: normal R$ 0,22
A10: P27 | B10: Caixa Patola PB-060 | C10: Usinainfo | D10: Caixa Patola PB-060 para Montagem 29 x 52 x 64 mm | E10: https://www.usinainfo.com.br/caixas-patola/caixa-patola-pb-060-para-montagem-29-x-52-x-64-mm-8284.html | F10: 5.94 | G10: preço da página | H10: 1 | I10: 1 | J10: =F10/H10*I10 -> 5.94 | K10: 27/10/2026 | L10: últimas unidades; cabe o PN532 (43 × 40 mm)
A11: P27 | B11: Fita de velcro 10 mm (rolo 10 m) | C11: Leroy Merlin | D11: Fita Fecho De Contato | Organizador De Cabos Preto | Rolo 10m X 10mm | E11: https://www.leroymerlin.com.br/fita-fecho-de-contato-%7C-organizador-de-cabos-preto-%7C-rolo-10m-x-10mm_1571751164 | F11: 18.9 | G11: preço do site | H11: 10 | I11: 0.3 | J11: =F11/H11*I11 -> 0.567 | K11: 27/10/2026 | L11: 0,3 m por pulseira; vendido por 47elétrica
A12: P45 | B12: Carregador USB 2 portas | C12: KaBuM | D12: Carregador De Tomada Universal USB Kaidi, 2 portas, Branco - Kd-301 | E12: https://www.kabum.com.br/produto/394690/carregador-de-tomada-universal-usb-kaidi-carregador-domestico-2-portas-branco-kd-301 | F12: 27.4 | G12: Pix | H12: 1 | I12: 1 | J12: =F12/H12*I12 -> 27.4 | K12: 27/10/2026 | L12: vendido por Assistec
