Workbook

Sheet Resumo
A1: Pick-to-Light: projeto inteiro feito pela equipe interna
A2: 40 estações: Medicamento (ruas 03 a 22, Asi 3) e Perfumaria (ruas 26 a 45, Asi 1). Arquitetura A 12 V com confirmação pelo coletor. Valores em reais, preços de mercado de outubro de 2026. Software não incluído.
A4: Item | B4: Valor (R$) | C4: Observação
A5: Materiais e infraestrutura | B5: =Projeto!E24 -> 222482.89 | C5: módulos, nós, concentradores, cabos, rede, energia, frete
A6: Mão de obra interna e treinamento | B6: =Projeto!E35 -> 82272.604 | C6: montagem, instalação, comissionamento e treinamento
A7: Total do projeto | B7: =B5+B6 -> 304755.49
A8: Contingência | B8: =B7*Premissas!$B$9 -> 30475.549 | C8: percentual na aba Premissas
A9: TOTAL COM CONTINGÊNCIA | B9: =B7+B8 -> 335231.04 | C9: valor para aprovação
A10: Por estação (com contingência) | B10: =B9/COUNT(Estações!$C$5:$C$44) -> 8380.776
A12: Projeção futura: RFID (não incluído no total acima)
A13: Implantação do RFID nas 40 estações (com contingência) | B13: ='RFID futuro'!E13 -> 36343.772 | C13: tags nas caixas, pulseiras, carregadores e montagem
A14: Tempo de operador liberado por mês | B14: ='RFID futuro'!B27 -> 660 | C14: premissa de tempo por leitura a medir na POC
A15: Valor do tempo liberado por mês | B15: ='RFID futuro'!B29 -> 16273.98
A16: Retorno do investimento no RFID | B16: ='RFID futuro'!B30 -> 2.2332442 | C16: detalhe por etapa na aba RFID futuro
A18: Quantidades principais
A19: Módulos Q (com reserva) | B19: =Projeto!C6 -> 1408
A20: Nós de coluna (com reserva) | B20: =Projeto!C7 -> 440
A21: Módulos E+Q (com reserva) | B21: =Projeto!C8 -> 277
A22: Concentradores (com reserva) | B22: =Projeto!C9 -> 44
A23: Horas de mão de obra interna | B23: =Projeto!C35 -> 2402.375
A25: Abas: Projeto (itens e mão de obra) · RFID futuro (custo, etapas, ganho e retorno) · Estações (dados das 40 estações) · Premissas (entradas em azul).

Sheet Premissas
A1: Premissas
A2: Entradas em azul; fundo amarelo = premissas principais. Valores do orçamento completo (Orcamento_PTL.xlsx), fontes na coluna D. Alterar aqui recalcula as outras abas.
A4: Premissa | B4: Valor | C4: Unidade | D4: Fonte / observação
A5: Custos e percentuais
A6: Custo-hora da equipe interna (técnico) | B6: 34.930552 | C6: R$/h | D6: salário médio de técnico eletrônico (salario.com.br, CAGED 08/10/2026) × 2 de encargos ÷ 163 h
A7: Custo-hora do operador da estação | B7: 24.657546 | C7: R$/h | D7: salário médio de auxiliar de logística (salario.com.br, CAGED 08/10/2026) × 2 de encargos ÷ 163 h
A8: Frete das compras | B8: 0.05 | C8: % | D8: estimativa sobre peças e infraestrutura
A9: Contingência do projeto | B9: 0.1 | C9: % | D9: imprevistos de instalação e variação de preço
A11: RFID (melhoria futura): implantação
A12: Frota de caixas retornáveis | B12: 5000 | C12: caixas | D12: estimativa: ~1,7 × 3.000 volumes/dia. CONFIRMAR com a operação
A13: Tag NFC por caixa | B13: 2.87 | C13: R$/un | D13: orçamento completo, aba RFID-futuro
A14: Associação tag ↔ caixa (cadastro inicial) | B14: 30 | C14: s/caixa | D14: estimativa
A15: Pulseiras por estação | B15: 2.2 | C15: un | D15: 2 por estação (uma carregando) + 10% de reserva
A16: Pulseira NFC (ESP32-C3 + PN532 + bateria) | B16: 127.54 | C16: R$/un | D16: orçamento completo, aba RFID-futuro
A17: Carregador USB das pulseiras (1 por estação) | B17: 35 | C17: R$/un | D17: orçamento completo, aba RFID-futuro
A18: Montagem por pulseira | B18: 1.5 | C18: h/un | D18: estimativa
A20: RFID (melhoria futura): ganho
A21: Volumes por dia (as duas linhas) | B21: 3000 | C21: volumes | D21: informado pela operação
A22: Estações visitadas por volume (média) | B22: 12 | C22: estações | D22: simulador, aba Operação completa: 20 itens por volume espalhados pelas 20 estações da linha
A23: Leituras de etiqueta por visita | B23: 2 | C23: leituras | D23: abrir e fechar a caixa na estação
A24: Tempo economizado por leitura com a pulseira | B24: 1.5 | C24: s | D24: PREMISSA A MEDIR NA POC: pegar o coletor, mirar e apertar o gatilho × encostar a mão na caixa
A25: Dias de operação por mês | B25: 22 | C25: dias | D25: CONFIRMAR com a operação
A27: O ganho do RFID é tempo de operador liberado. Ele vira economia em reais quando reduz hora extra ou pessoas, ou quando permite absorver mais volume com a mesma equipe.

Sheet Estações
A1: Estações (40)
A2: Fonte: tabela wms_endereco de 23/10/2026. As quantidades de compra na aba Projeto somam estas colunas com 10% de reserva.
A4: Estação (rua) | B4: Segmento | C4: Endereços | D4: Módulos Q (alto giro 0-3) | E4: Nós de coluna | F4: E+Q andares 4-5 | G4: E+Q zonas baixo giro | H4: Concentrador
A5: 03 | B5: Medicamento | C5: 131 | D5: 29 | E5: 10 | F5: 2 | G5: 2 | H5: 1
A6: 04 | B6: Medicamento | C6: 201 | D6: 29 | E6: 10 | F6: 2 | G6: 4 | H6: 1
A7: 05 | B7: Medicamento | C7: 209 | D7: 29 | E7: 10 | F7: 2 | G7: 4 | H7: 1
A8: 06 | B8: Medicamento | C8: 209 | D8: 29 | E8: 10 | F8: 2 | G8: 4 | H8: 1
A9: 07 | B9: Medicamento | C9: 209 | D9: 29 | E9: 10 | F9: 2 | G9: 4 | H9: 1
A10: 08 | B10: Medicamento | C10: 205 | D10: 29 | E10: 10 | F10: 2 | G10: 4 | H10: 1
A11: 09 | B11: Medicamento | C11: 241 | D11: 29 | E11: 10 | F11: 2 | G11: 5 | H11: 1
A12: 10 | B12: Medicamento | C12: 237 | D12: 29 | E12: 10 | F12: 2 | G12: 5 | H12: 1
A13: 11 | B13: Medicamento | C13: 205 | D13: 29 | E13: 10 | F13: 2 | G13: 4 | H13: 1
A14: 12 | B14: Medicamento | C14: 209 | D14: 29 | E14: 10 | F14: 2 | G14: 4 | H14: 1
A15: 13 | B15: Medicamento | C15: 203 | D15: 29 | E15: 10 | F15: 2 | G15: 4 | H15: 1
A16: 14 | B16: Medicamento | C16: 209 | D16: 29 | E16: 10 | F16: 2 | G16: 4 | H16: 1
... A44: 45 | B44: Perfumaria | C44: 181 | D44: 35 | E44: 10 | F44: 2 | G44: 4 | H44: 1
A45: Total | C45: =SUM(C5:C44) -> 7981 | D45: =SUM(D5:D44) -> 1280 | E45: =SUM(E5:E44) -> 400 | F45: =SUM(F5:F44) -> 80 | G45: =SUM(G5:G44) -> 171 | H45: =SUM(H5:H44) -> 40

Sheet Projeto
A1: Projeto inteiro: 40 estações, equipe interna
A2: Arquitetura A (12 V): módulos montados pela equipe interna, concentrador por estação e barramento RS-485. Quantidades com 10% de reserva. Software fora desta planilha.
A4: Item | B4: Base de cálculo | C4: Qtd | D4: Preço unit. (R$) | E4: Total (R$)
A5: Materiais e infraestrutura
A6: Módulos Q (alto giro 0-3) | B6: endereços alto giro 0-3 × (1 + reserva) | C6: 1408 | D6: 45.141705 | E6: =C6*D6 -> 63559.521
A7: Nós de coluna (alto giro) | B7: prédios do alto giro × (1 + reserva) | C7: 440 | D7: 96.8 | E7: =C7*D7 -> 42592
A8: Módulos E+Q (A4/A5 + zonas baixo giro) | B8: displays E+Q × (1 + reserva) | C8: 277 | D8: 134.95 | E8: =C8*D8 -> 37381.15
A9: Concentradores 12 V | B9: 1 por estação × (1 + reserva) | C9: 44 | D9: 549.81043 | E9: =C9*D9 -> 24191.659
A10: Cabo de barramento Cat5e (m) | B10: segmentos × m por segmento + 2 saídas × m de saída por estação | C10: 2433 | D10: 4.0308525 | E10: =C10*D10 -> 9807.064
A11: Plugs RJ45 do barramento | B11: 2 por segmento + 4 por estação (saídas) | C11: 1462 | D11: 0.8 | E11: =C11*D11 -> 1169.6
A12: Canaleta / perfil de fixação (m) | B12: prédios alto giro × (largura × linhas + descida) + 2 lados × corredor + travessia, por estação | C12: 1080 | D12: 9 | E12: =C12*D12 -> 9720
A13: Fixações diversas | B13: 1 kit por estação | C13: 40 | D13: 40 | E13: =C13*D13 -> 1600
A14: Sinal luminoso de baixo giro | B14: 1 por estação, ao lado da posição de pega | C14: 40 | D14: 45 | E14: =C14*D14 -> 1800
A15: Cabo de rede até a estação (m) | B15: metros por estação | C15: 2000 | D15: 4.0308525 | E15: =C15*D15 -> 8061.7049
A16: Switch 24 portas | B16: estações ÷ portas por switch (arredondado para cima) | C16: 2 | D16: 769.32 | E16: =C16*D16 -> 1538.64
A17: Nobreak do switch | B17: 1 por switch | C17: 2 | D17: 368.1 | E17: =C17*D17 -> 736.2
... A22: Bancada de eletrônica (solda, multímetro) | B22: 1 kit (compra única) | C22: 1 | D22: 700 | E22: =C22*D22 -> 700
A23: Frete das compras | B23: % sobre os materiais acima (aba Premissas) | D23: =Premissas!$B$8 -> 0.05 | E23: =SUM(E6:E22)*D23 -> 10594.423
A24: Subtotal materiais | E24: =SUM(E6:E23) -> 222482.89
A26: Mão de obra interna e treinamento
A27: Montagem Módulos Q (h) | B27: módulos × h/un | C27: 352 | D27: =Premissas!$B$6 -> 34.930552 | E27: =C27*D27 -> 12295.554
A28: Montagem Nós de coluna (h) | B28: nós × h/un | C28: 330 | D28: =Premissas!$B$6 -> 34.930552 | E28: =C28*D28 -> 11527.082
A29: Montagem Módulos E+Q (h) | B29: módulos × h/un | C29: 277 | D29: =Premissas!$B$6 -> 34.930552 | E29: =C29*D29 -> 9675.7629
A30: Montagem Concentradores (h) | B30: concentradores × h/un | C30: 88 | D30: =Premissas!$B$6 -> 34.930552 | E30: =C30*D30 -> 3073.8886
A31: Instalação nas estações (h) | B31: (fixo por estação + Q + nós + E+Q + canaleta) × fator hora extra | C31: 939.375 | D31: =Premissas!$B$6 -> 34.930552 | E31: =C31*D31 -> 32812.887
A32: Testes e comissionamento (h) | B32: estações × h/estação × fator hora extra | C32: 240 | D32: =Premissas!$B$6 -> 34.930552 | E32: =C32*D32 -> 8383.3325
A33: Treinamento dos operadores (h) | B33: estações × turnos × h por operador | C33: 160 | D33: =Premissas!$B$7 -> 24.657546 | E33: =C33*D33 -> 3945.2074
A34: Treinamento da manutenção (h) | B34: total da equipe | C34: 16 | D34: =Premissas!$B$6 -> 34.930552 | E34: =C34*D34 -> 558.88883
A35: Subtotal mão de obra e treinamento | C35: =SUM(C27:C34) -> 2402.375 | E35: =SUM(E27:E34) -> 82272.604
A37: TOTAL DO PROJETO (materiais + mão de obra) | E37: =E24+E35 -> 304755.49

Sheet RFID futuro
A1: Projeção futura: identificação por RFID
A2: Melhoria futura, fora do investimento inicial: tag NFC em cada caixa e pulseira no operador. A caixa abre e fecha quando o operador encosta a mão, sem o gatilho do coletor. O hardware e o software do projeto já ficam preparados. As cerca de 80 h de software do RFID não estão somadas, como no restante desta planilha.
A4: 1. Custo de implantação nas 40 estações
A5: Item | B5: Base de cálculo | C5: Qtd | D5: Preço unit. (R$) | E5: Total (R$)
A6: Tags NFC nas caixas retornáveis | B6: frota de caixas | C6: =Premissas!$B$12 -> 5000 | D6: =Premissas!$B$13 -> 2.87 | E6: =C6*D6 -> 14350
A7: Associação tag ↔ caixa (h) | B7: frota × segundos por caixa ÷ 3.600 | C7: =Premissas!$B$12*Premissas!$B$14/3600 -> 41.666667 | D7: =Premissas!$B$6 -> 34.930552 | E7: =C7*D7 -> 1455.4397
A8: Pulseiras NFC | B8: estações × pulseiras por estação (arredondado para cima) | C8: =ROUNDUP(COUNT(Estações!$C$5:$C$44)*Premissas!$B$15,0) -> 88 | D8: =Premissas!$B$16 -> 127.54 | E8: =C8*D8 -> 11223.52
A9: Carregadores USB | B9: 1 por estação | C9: =COUNT(Estações!$C$5:$C$44) -> 40 | D9: =Premissas!$B$17 -> 35 | E9: =C9*D9 -> 1400
A10: Montagem das pulseiras (h) | B10: pulseiras × horas por pulseira | C10: =C8*Premissas!$B$18 -> 132 | D10: =Premissas!$B$6 -> 34.930552 | E10: =C10*D10 -> 4610.8329
A11: Subtotal RFID | E11: =SUM(E6:E10) -> 33039.793
A12: Contingência | B12: % da aba Premissas | D12: =Premissas!$B$9 -> 0.1 | E12: =E11*D12 -> 3303.9793
A13: TOTAL RFID COM CONTINGÊNCIA | E13: =E11+E12 -> 36343.772
A15: 2. Implantação em etapas
A16: Etapa | B16: Estações | C16: Tags NFC | D16: Pulseiras | E16: Carregadores | F16: Horas (assoc. + montagem) | G16: Custo com contingência (R$)
A17: Etapa 1: estações da POC (04 e 27) | B17: 2 | C17: =ROUND(Premissas!$B$12*B17/COUNT(Estações!$C$5:$C$44),0) -> 250 | D17: =ROUNDUP(B17*Premissas!$B$15,0) -> 5 | E17: =B17 -> 2 | F17: =C17*Premissas!$B$14/3600+D17*Premissas!$B$18 -> 9.5833333 | G17: =(C17*Premissas!$B$13+D17*Premissas!$B$16+E17*Premissas!$B$17+F17*Premissas!$B$6)*(1+Premissas!$B$9) -> 1935.9462
A18: Etapa 2: demais estações de Medicamento | B18: 19 | C18: =ROUND(Premissas!$B$12*B18/COUNT(Estações!$C$5:$C$44),0) -> 2375 | D18: =ROUNDUP(B18*Premissas!$B$15,0) -> 42 | E18: =B18 -> 19 | F18: =C18*Premissas!$B$14/3600+D18*Premissas!$B$18 -> 82.791667 | G18: =(C18*Premissas!$B$13+D18*Premissas!$B$16+E18*Premissas!$B$17+F18*Premissas!$B$6)*(1+Premissas!$B$9) -> 17302.877
A19: Etapa 3: demais estações de Perfumaria | B19: 19 | C19: =ROUND(Premissas!$B$12*B19/COUNT(Estações!$C$5:$C$44),0) -> 2375 | D19: =ROUNDUP(B19*Premissas!$B$15,0) -> 42 | E19: =B19 -> 19 | F19: =C19*Premissas!$B$14/3600+D19*Premissas!$B$18 -> 82.791667 | G19: =(C19*Premissas!$B$13+D19*Premissas!$B$16+E19*Premissas!$B$17+F19*Premissas!$B$6)*(1+Premissas!$B$9) -> 17302.877
A20: Total das etapas | B20: =SUM(B17:B19) -> 40 | C20: =SUM(C17:C19) -> 5000 | D20: =SUM(D17:D19) -> 89 | E20: =SUM(E17:E19) -> 40 | F20: =SUM(F17:F19) -> 175.16667 | G20: =SUM(G17:G19) -> 36541.701
A21: Tags divididas pela frota na proporção das estações de cada etapa. Se as caixas circulam entre as duas linhas, a frota inteira precisa de tag já na etapa 2. Pulseiras arredondadas para cima em cada etapa, por isso o total das etapas pode passar um pouco do item 1.
A23: 3. Ganho e retorno
A24: Indicador | B24: Valor | C24: Unidade
A25: Leituras de etiqueta por dia | B25: =Premissas!$B$21*Premissas!$B$22*Premissas!$B$23 -> 72000 | C25: leituras
A26: Tempo de operador liberado por dia | B26: =B25*Premissas!$B$24/3600 -> 30 | C26: h/dia
A27: Tempo de operador liberado por mês | B27: =B26*Premissas!$B$25 -> 660 | C27: h/mês
A28: Equivalente em operadores | B28: =B27/163 -> 4.0490798 | C28: operadores (163 h/mês)
A29: Valor do tempo liberado por mês | B29: =B27*Premissas!$B$7 -> 16273.98 | C29: R$/mês
A30: Retorno do investimento no RFID (40 estações) | B30: =IF(B29>0,E13/B29,0) -> 2.2332442 | C30: meses
A32: Etapa | B32: Estações | C32: Investimento acumulado (R$) | D32: Ganho por mês (R$) | E32: Ganho acumulado por mês (R$) | F32: Retorno da etapa (meses)
A33: Etapa 1: estações da POC (04 e 27) | B33: =B17 -> 2 | C33: =SUM($G$17:G17) -> 1935.9462 | D33: =$B$29*B33/COUNT(Estações!$C$5:$C$44) -> 813.69902 | E33: =SUM($D$33:D33) -> 813.69902 | F33: =IF(D33>0,G17/D33,0) -> 2.3791921
A34: Etapa 2: demais estações de Medicamento | B34: =B18 -> 19 | C34: =SUM($G$17:G18) -> 19238.824 | D34: =$B$29*B34/COUNT(Estações!$C$5:$C$44) -> 7730.1407 | E34: =SUM($D$33:D34) -> 8543.8397 | F34: =IF(D34>0,G18/D34,0) -> 2.2383652
A35: Etapa 3: demais estações de Perfumaria | B35: =B19 -> 19 | C35: =SUM($G$17:G19) -> 36541.701 | D35: =$B$29*B35/COUNT(Estações!$C$5:$C$44) -> 7730.1407 | E35: =SUM($D$33:D35) -> 16273.98 | F35: =IF(D35>0,G19/D35,0) -> 2.2383652
A36: O ganho de cada etapa é proporcional às estações cobertas. Todos os tempos são premissas (aba Premissas); o tempo economizado por leitura deve ser medido na POC antes de decidir o RFID.
